comfyui_mcp/__about__.py
comfyui_mcp/__init__.py
comfyui_mcp/argument_parser.py
comfyui_mcp/base_types.py
comfyui_mcp/function_utils.py
comfyui_mcp/server.py
comfyui_mcp/workflow_loader.py
comfyui_mcp/workflow_utils.py
comfyui_mcp-0.0.4.dist-info/METADATA
comfyui_mcp-0.0.4.dist-info/WHEEL
comfyui_mcp-0.0.4.dist-info/licenses/LICENSE.txt
comfyui_mcp-0.0.4.dist-info/RECORD
