Metadata-Version: 2.4
Name: comfyui-mcp
Version: 0.0.4
Project-URL: Documentation, https://github.com/ModdingFox/comfyui_mcp#README.md
Project-URL: Issues, https://github.com/ModdingFox/comfyui_mcp/issues
Project-URL: Source, https://github.com/ModdingFox/comfyui_mcp
Author-email: Tyst Marin <moddingfox@foxtek.us>
License-Expression: MIT
License-File: LICENSE.txt
Classifier: Development Status :: 4 - Beta
Classifier: Programming Language :: Python
Classifier: Programming Language :: Python :: 3.11
Classifier: Programming Language :: Python :: 3.12
Classifier: Programming Language :: Python :: 3.13
Classifier: Programming Language :: Python :: Implementation :: CPython
Classifier: Programming Language :: Python :: Implementation :: PyPy
Requires-Python: >=3.11
Requires-Dist: comfyui-utils>=0.0.1
Requires-Dist: fastmcp>=2.13.0.2
Requires-Dist: jsonargparse
